egeek_tools/__init__.py
egeek_tools/datatable.py
egeek_tools-1.0.0.dist-info/METADATA
egeek_tools-1.0.0.dist-info/WHEEL
egeek_tools-1.0.0.dist-info/top_level.txt
egeek_tools-1.0.0.dist-info/RECORD
