Metadata-Version: 2.1
Name: egeek_tools
Version: 1.0.0
Summary: Fastapi Datatable
Author: vicram10
Author-email: victor.ramirez@egeek.com.py
Classifier: Programming Language :: Python :: 3.10
Classifier: License :: OSI Approved :: MIT License
Classifier: Operating System :: OS Independent
Requires-Python: >=3.10
Requires-Dist: SQLAlchemy >=2.0
